[
  {
    "uf": "AP",
    "codigo": "1600105",
    "municipio": "Amapá"
  },
  {
    "uf": "AP",
    "codigo": "1600204",
    "municipio": "Calçoene"
  },
  {
    "uf": "AP",
    "codigo": "1600212",
    "municipio": "Cutias"
  },
  {
    "uf": "AP",
    "codigo": "1600238",
    "municipio": "Ferreira Gomes"
  },
  {
    "uf": "AP",
    "codigo": "1600253",
    "municipio": "Itaubal"
  },
  {
    "uf": "AP",
    "codigo": "1600279",
    "municipio": "Laranjal do Jari"
  },
  {
    "uf": "AP",
    "codigo": "1600303",
    "municipio": "Macapá"
  },
  {
    "uf": "AP",
    "codigo": "1600402",
    "municipio": "Mazagão"
  },
  {
    "uf": "AP",
    "codigo": "1600501",
    "municipio": "Oiapoque"
  },
  {
    "uf": "AP",
    "codigo": "1600154",
    "municipio": "Pedra Branca do Amapari"
  },
  {
    "uf": "AP",
    "codigo": "1600535",
    "municipio": "Porto Grande"
  },
  {
    "uf": "AP",
    "codigo": "1600550",
    "municipio": "Pracuúba"
  },
  {
    "uf": "AP",
    "codigo": "1600600",
    "municipio": "Santana"
  },
  {
    "uf": "AP",
    "codigo": "1600055",
    "municipio": "Serra do Navio"
  },
  {
    "uf": "AP",
    "codigo": "1600709",
    "municipio": "Tartarugalzinho"
  },
  {
    "uf": "AP",
    "codigo": "1600808",
    "municipio": "Vitória do Jari"
  }
]